pnu_wis-1.0.1.data/data/man/man1/wis.1.gz
pnu_wis-1.0.1.data/data/share/wis/fetch-db-RR.sh
pnu_wis-1.0.1.data/data/share/wis/fetch-db-WHOIS.sh
wis/__init__.py
wis/main.py
pnu_wis-1.0.1.dist-info/License
pnu_wis-1.0.1.dist-info/METADATA
pnu_wis-1.0.1.dist-info/WHEEL
pnu_wis-1.0.1.dist-info/entry_points.txt
pnu_wis-1.0.1.dist-info/top_level.txt
pnu_wis-1.0.1.dist-info/RECORD
